pdegen/__init__.py
pdegen/generate.py
pdegen/interface.py
pdegen/problems/__init__.py
pdegen/problems/adr.py
pdegen/problems/burgers.py
pdegen/problems/heat.py
pdegen/problems/utils.py
pdegen-0.0.1.dist-info/LICENSE
pdegen-0.0.1.dist-info/METADATA
pdegen-0.0.1.dist-info/WHEEL
pdegen-0.0.1.dist-info/top_level.txt
pdegen-0.0.1.dist-info/RECORD
